{
    "YOU KNOW ME": {
        "Race": "Angel",
        "Archetype": "",
        "Role": "Hero",
        "Title": "",
        "Size": "5FT",
        "Stats": {
            "Strength": "Weak",
            "Speed": "Peak Human",
            "Durability": "Superhuman",
            "IQ": "Omniscient",
            "Fight": "Darwizzy"
        },
        "Weapons": {
            "Weapon": "Stick",
            "Weapon Mastery": "Transcendent"
        },
        "Powers": {
            "Power": "Superman",
            "Power Mastery": "Omnipotent"
        },
        "Extra": {
            "Weakness": "",
            "Chaos Force": "",
            "Chaos Factor": ""
        },
        "Enchantment": "",
        "Image": "S1 - YOU KNOW ME.png"
    },
    "Trevor Wright": {
        "Race": "Demi God",
        "Archetype": "",
        "Role": "Hero",
        "Title": "",
        "Size": "8FT",
        "Stats": {
            "Strength": "Peak Human",
            "Speed": "Mid",
            "Durability": "Superhuman",
            "IQ": "Genius",
            "Fight": "Meta-Martial"
        },
        "Weapons": {
            "Weapon": "",
            "Weapon Mastery": "Transcendent"
        },
        "Powers": {
            "Power": "",
            "Power Mastery": "Omnipotent"
        },
        "Extra": {
            "Weakness": "",
            "Chaos Force": "",
            "Chaos Factor": ""
        },
        "Enchantment": "",
        "Image": "S1 - Trevor Wright.png"
    },
    "Dawit": {
        "Race": "Earth God",
        "Archetype": "",
        "Role": "Villain",
        "Title": "",
        "Size": "4.5FT",
        "Stats": {
            "Strength": "Superhuman",
            "Speed": "Light Speed",
            "Durability": "Darwizzy",
            "IQ": "Prodigious",
            "Fight": "Champion"
        },
        "Weapons": {
            "Weapon": "",
            "Weapon Mastery": "Transcendent"
        },
        "Powers": {
            "Power": "Foresight",
            "Power Mastery": "Omnipotent"
        },
        "Extra": {
            "Weakness": "",
            "Chaos Force": "",
            "Chaos Factor": ""
        },
        "Enchantment": "",
        "Image": "S1 - Dawit.png"
    },
    "Sky M": {
        "Race": "Fairy",
        "Archetype": "",
        "Role": "Villain",
        "Title": "",
        "Size": "6.5FT",
        "Stats": {
            "Strength": "Cosmic",
            "Speed": "Superhuman",
            "Durability": "Mid",
            "IQ": "Omniscient",
            "Fight": "Champion"
        },
        "Weapons": {
            "Weapon": "Katana",
            "Weapon Mastery": "Transcendent"
        },
        "Powers": {
            "Power": "Fire control",
            "Power Mastery": "Omnipotent"
        },
        "Extra": {
            "Weakness": "",
            "Chaos Force": "",
            "Chaos Factor": ""
        },
        "Enchantment": "",
        "Image": "S1 - Sky M.png"
    },
    "It's me Maui": {
        "Race": "Demi God",
        "Archetype": "",
        "Role": "Hero",
        "Title": "",
        "Size": "6.5FT",
        "Stats": {
            "Strength": "Weak",
            "Speed": "Peak Human",
            "Durability": "Nuclear",
            "IQ": "Omniscient",
            "Fight": "Darwizzy"
        },
        "Weapons": {
            "Weapon": "Stick",
            "Weapon Mastery": "Transcendent"
        },
        "Powers": {
            "Power": "Summoning",
            "Power Mastery": "Omnipotent"
        },
        "Extra": {
            "Weakness": "",
            "Chaos Force": "",
            "Chaos Factor": ""
        },
        "Enchantment": "",
        "Image": "S1 - It's me Maui.png"
    },
    "Spacemuffi": {
        "Race": "Vampire",
        "Archetype": "",
        "Role": "Hero",
        "Title": "",
        "Size": "5FT",
        "Stats": {
            "Strength": "Herculean",
            "Speed": "Supersonic",
            "Durability": "Nuclear",
            "IQ": "Genius",
            "Fight": "Champion"
        },
        "Weapons": {
            "Weapon": "",
            "Weapon Mastery": "Transcendent"
        },
        "Powers": {
            "Power": "Teleportation",
            "Power Mastery": "Omnipotent"
        },
        "Extra": {
            "Weakness": "",
            "Chaos Force": "",
            "Chaos Factor": ""
        },
        "Enchantment": "",
        "Image": "S1 - Spacemuffi.png"
    },
    "Nerdy_happy_evan": {
        "Race": "Goblin",
        "Archetype": "",
        "Role": "Villain",
        "Title": "",
        "Size": "8.5FT",
        "Stats": {
            "Strength": "Weak",
            "Speed": "Old man",
            "Durability": "Nuclear",
            "IQ": "Genius",
            "Fight": "Champion"
        },
        "Weapons": {
            "Weapon": "Thor's Hammer",
            "Weapon Mastery": "Transcendent"
        },
        "Powers": {
            "Power": "Healing",
            "Power Mastery": "Omnipotent"
        },
        "Extra": {
            "Weakness": "",
            "Chaos Force": "",
            "Chaos Factor": ""
        },
        "Enchantment": "",
        "Image": "S1 - Nerdy_happy_evan.png"
    },
    "Sethington": {
        "Race": "Angel",
        "Archetype": "",
        "Role": "Villain",
        "Title": "",
        "Size": "8FT",
        "Stats": {
            "Strength": "Superhuman",
            "Speed": "Old man",
            "Durability": "Mid",
            "IQ": "Omniscient",
            "Fight": "Mid"
        },
        "Weapons": {
            "Weapon": "Diamond Sword",
            "Weapon Mastery": "Transcendent"
        },
        "Powers": {
            "Power": "Mindcontrol",
            "Power Mastery": "Omnipotent"
        },
        "Extra": {
            "Weakness": "",
            "Chaos Force": "",
            "Chaos Factor": ""
        },
        "Enchantment": "",
        "Image": "S1 - Sethington.png"
    },
    "Giordy": {
        "Race": "Human",
        "Archetype": "",
        "Role": "Villain",
        "Title": "",
        "Size": "5FT",
        "Stats": {
            "Strength": "Superhuman",
            "Speed": "Supersonic",
            "Durability": "Darwizzy",
            "IQ": "Prodigious",
            "Fight": "Champion"
        },
        "Weapons": {
            "Weapon": "Diamond Sword",
            "Weapon Mastery": "Transcendent"
        },
        "Powers": {
            "Power": "",
            "Power Mastery": "Omnipotent"
        },
        "Extra": {
            "Weakness": "",
            "Chaos Force": "",
            "Chaos Factor": ""
        },
        "Enchantment": "",
        "Image": "S1 - Giordy.png"
    },
    "Cavorce": {
        "Race": "Goblin",
        "Archetype": "",
        "Role": "Hero",
        "Title": "",
        "Size": "9.5FT",
        "Stats": {
            "Strength": "Peak Human",
            "Speed": "Superhuman",
            "Durability": "Cosmic",
            "IQ": "Dumb",
            "Fight": "Darwizzy"
        },
        "Weapons": {
            "Weapon": "Gun",
            "Weapon Mastery": "Transcendent"
        },
        "Powers": {
            "Power": "",
            "Power Mastery": "Omnipotent"
        },
        "Extra": {
            "Weakness": "",
            "Chaos Force": "",
            "Chaos Factor": ""
        },
        "Enchantment": "",
        "Image": "S1 - Cavorce.png"
    },
    "TheGuywhoDrums": {
        "Race": "Vampire",
        "Archetype": "",
        "Role": "Hero",
        "Title": "",
        "Size": "8.5FT",
        "Stats": {
            "Strength": "Peak Human",
            "Speed": "Old man",
            "Durability": "Mid",
            "IQ": "Genius",
            "Fight": "Darwizzy"
        },
        "Weapons": {
            "Weapon": "",
            "Weapon Mastery": "Transcendent"
        },
        "Powers": {
            "Power": "Healing",
            "Power Mastery": "Omnipotent"
        },
        "Extra": {
            "Weakness": "",
            "Chaos Force": "",
            "Chaos Factor": ""
        },
        "Enchantment": "",
        "Image": "S1 - TheGuywhoDrums.png"
    },
    "Mastro": {
        "Race": "Demi God",
        "Archetype": "",
        "Role": "Hero",
        "Title": "",
        "Size": "7.5FT",
        "Stats": {
            "Strength": "Cosmic",
            "Speed": "Superhuman",
            "Durability": "Superhuman",
            "IQ": "Dumb",
            "Fight": "Mid"
        },
        "Weapons": {
            "Weapon": "Light saber",
            "Weapon Mastery": "Transcendent"
        },
        "Powers": {
            "Power": "Thunder control",
            "Power Mastery": "Omnipotent"
        },
        "Extra": {
            "Weakness": "",
            "Chaos Force": "",
            "Chaos Factor": ""
        },
        "Enchantment": "",
        "Image": "S1 - Mastro.png"
    },
    "Pepsi Jackson": {
        "Race": "Vacuum Robot",
        "Archetype": "",
        "Role": "Villain",
        "Title": "",
        "Size": "4FT",
        "Stats": {
            "Strength": "Weak",
            "Speed": "Mid",
            "Durability": "Mid",
            "IQ": "Genius",
            "Fight": "Unbeatable"
        },
        "Weapons": {
            "Weapon": "Rocks",
            "Weapon Mastery": "Transcendent"
        },
        "Powers": {
            "Power": "",
            "Power Mastery": "Omnipotent"
        },
        "Extra": {
            "Weakness": "",
            "Chaos Force": "",
            "Chaos Factor": ""
        },
        "Enchantment": "",
        "Image": "S1 - Pepsi Jackson.png"
    },
    "Zay": {
        "Race": "Alien",
        "Archetype": "",
        "Role": "Villain",
        "Title": "",
        "Size": "8FT",
        "Stats": {
            "Strength": "Herculean",
            "Speed": "Supersonic",
            "Durability": "Nuclear",
            "IQ": "Genius",
            "Fight": "Peak Human"
        },
        "Weapons": {
            "Weapon": "Axe",
            "Weapon Mastery": "Transcendent"
        },
        "Powers": {
            "Power": "Shapeshifting",
            "Power Mastery": "Omnipotent"
        },
        "Extra": {
            "Weakness": "",
            "Chaos Force": "",
            "Chaos Factor": ""
        },
        "Enchantment": "",
        "Image": "S1 - Zay.png"
    },
    "The Hollow One": {
        "Race": "Angel",
        "Archetype": "",
        "Role": "Hero",
        "Title": "",
        "Size": "4FT",
        "Stats": {
            "Strength": "Mid",
            "Speed": "Superhuman",
            "Durability": "Darwizzy",
            "IQ": "Super Genius",
            "Fight": "Mid"
        },
        "Weapons": {
            "Weapon": "",
            "Weapon Mastery": "Transcendent"
        },
        "Powers": {
            "Power": "Asteroids Rain",
            "Power Mastery": "Omnipotent"
        },
        "Extra": {
            "Weakness": "",
            "Chaos Force": "",
            "Chaos Factor": ""
        },
        "Enchantment": "",
        "Image": "S1 - The Hollow One.png"
    },
    "Anto": {
        "Race": "Goblin",
        "Archetype": "",
        "Role": "Hero",
        "Title": "",
        "Size": "4FT",
        "Stats": {
            "Strength": "Weak",
            "Speed": "Old man",
            "Durability": "Cosmic",
            "IQ": "Dumb",
            "Fight": "Mid"
        },
        "Weapons": {
            "Weapon": "Rocks",
            "Weapon Mastery": "Transcendent"
        },
        "Powers": {
            "Power": "Invisibility",
            "Power Mastery": "Omnipotent"
        },
        "Extra": {
            "Weakness": "",
            "Chaos Force": "",
            "Chaos Factor": ""
        },
        "Enchantment": "",
        "Image": "S1 - Anto.png"
    },
    "Tokyo_Editz": {
        "Race": "Werewolf",
        "Archetype": "",
        "Role": "Hero",
        "Title": "",
        "Size": "8FT",
        "Stats": {
            "Strength": "Superhuman",
            "Speed": "Old Man",
            "Durability": "Superhuman",
            "IQ": "Dumb",
            "Fight": "Unbeatable"
        },
        "Weapons": {
            "Weapon": "Diamond Sword",
            "Weapon Mastery": "Transcendent"
        },
        "Powers": {
            "Power": "Shapeshifting",
            "Power Mastery": "Omnipotent"
        },
        "Extra": {
            "Weakness": "",
            "Chaos Force": "",
            "Chaos Factor": ""
        },
        "Enchantment": "",
        "Image": "S1 - Tokyo_Editz.png"
    },
    "JJK": {
        "Race": "Vampire",
        "Archetype": "",
        "Role": "Villain",
        "Title": "",
        "Size": "4.5FT",
        "Stats": {
            "Strength": "Boundless",
            "Speed": "Peak Human",
            "Durability": "Darwizzy",
            "IQ": "Dumb",
            "Fight": "Unbeatable"
        },
        "Weapons": {
            "Weapon": "Whip",
            "Weapon Mastery": "Transcendent"
        },
        "Powers": {
            "Power": "Flying",
            "Power Mastery": "Omnipotent"
        },
        "Extra": {
            "Weakness": "",
            "Chaos Force": "",
            "Chaos Factor": ""
        },
        "Enchantment": "",
        "Image": "S1 - JJK.png"
    },
    "Space Invader": {
        "Race": "Thunder God",
        "Archetype": "",
        "Role": "Hero",
        "Title": "",
        "Size": "10.5FT",
        "Stats": {
            "Strength": "Peak Human",
            "Speed": "Old man",
            "Durability": "Nuclear",
            "IQ": "Prodigious",
            "Fight": "Mid"
        },
        "Weapons": {
            "Weapon": "Iron man suit",
            "Weapon Mastery": "Transcendent"
        },
        "Powers": {
            "Power": "Time Travel + Thunder control + Superman",
            "Power Mastery": "Omnipotent"
        },
        "Extra": {
            "Weakness": "",
            "Chaos Force": "",
            "Chaos Factor": ""
        },
        "Enchantment": "",
        "Image": "S1 - Space Invader.png"
    },
    "Fox The Pizza God": {
        "Race": "Ninja",
        "Archetype": "",
        "Role": "Villain",
        "Title": "",
        "Size": "6.5FT",
        "Stats": {
            "Strength": "Boundless",
            "Speed": "Light Speed",
            "Durability": "Superhuman",
            "IQ": "Genius",
            "Fight": "Champion"
        },
        "Weapons": {
            "Weapon": "Stick",
            "Weapon Mastery": "Transcendent"
        },
        "Powers": {
            "Power": "Genjutsu + Resurrection",
            "Power Mastery": "Omnipotent"
        },
        "Extra": {
            "Weakness": "",
            "Chaos Force": "",
            "Chaos Factor": ""
        },
        "Enchantment": "",
        "Image": "S1 - Fox The Pizza God.png"
    },
    "Ionutsj": {
        "Race": "Human",
        "Archetype": "",
        "Role": "Villain",
        "Title": "",
        "Size": "6.5FT",
        "Stats": {
            "Strength": "Superhuman",
            "Speed": "Mid",
            "Durability": "Nuclear",
            "IQ": "Prodigious",
            "Fight": "Champion"
        },
        "Weapons": {
            "Weapon": "Infinity Gauntlet",
            "Weapon Mastery": "Transcendent"
        },
        "Powers": {
            "Power": "",
            "Power Mastery": "Omnipotent"
        },
        "Extra": {
            "Weakness": "",
            "Chaos Force": "",
            "Chaos Factor": ""
        },
        "Enchantment": "",
        "Image": "S1 - Ionutsj.png"
    },
    "Gutter Goblin": {
        "Race": "robot",
        "Archetype": "",
        "Role": "Hero",
        "Title": "",
        "Size": "4.5FT",
        "Stats": {
            "Strength": "Weak",
            "Speed": "Supersonic",
            "Durability": "Nuclear",
            "IQ": "Prodigious",
            "Fight": "Mid"
        },
        "Weapons": {
            "Weapon": "",
            "Weapon Mastery": "Transcendent"
        },
        "Powers": {
            "Power": "Cloning",
            "Power Mastery": "Omnipotent"
        },
        "Extra": {
            "Weakness": "",
            "Chaos Force": "",
            "Chaos Factor": ""
        },
        "Enchantment": "",
        "Image": "S1 - Gutter Goblin.png"
    },
    "KingCantona": {
        "Race": "Fairy",
        "Archetype": "",
        "Role": "Villain",
        "Title": "",
        "Size": "4FT",
        "Stats": {
            "Strength": "Weak",
            "Speed": "Light Speed",
            "Durability": "Cosmic",
            "IQ": "Dumb",
            "Fight": "Mid"
        },
        "Weapons": {
            "Weapon": "Wolverine Claws",
            "Weapon Mastery": "Transcendent"
        },
        "Powers": {
            "Power": "Resurrection",
            "Power Mastery": "Omnipotent"
        },
        "Extra": {
            "Weakness": "",
            "Chaos Force": "",
            "Chaos Factor": ""
        },
        "Enchantment": "",
        "Image": "S1 - KingCantona.png"
    },
    "Legit": {
        "Race": "Angel",
        "Archetype": "",
        "Role": "Hero",
        "Title": "",
        "Size": "9.5FT",
        "Stats": {
            "Strength": "Mid",
            "Speed": "Old man",
            "Durability": "Darwizzy",
            "IQ": "Super Genius",
            "Fight": "Mid"
        },
        "Weapons": {
            "Weapon": "Light saber",
            "Weapon Mastery": "Transcendent"
        },
        "Powers": {
            "Power": "Foresight + Heat Vision",
            "Power Mastery": "Omnipotent"
        },
        "Extra": {
            "Weakness": "",
            "Chaos Force": "",
            "Chaos Factor": ""
        },
        "Enchantment": "",
        "Image": "S1 - Legit.png"
    },
    "IRaulLozano": {
        "Race": "Human",
        "Archetype": "",
        "Role": "Villain",
        "Title": "",
        "Size": "7.5FT",
        "Stats": {
            "Strength": "Superhuman",
            "Speed": "Old man",
            "Durability": "Mid",
            "IQ": "Mid",
            "Fight": "Peak Human"
        },
        "Weapons": {
            "Weapon": "Grenade Launcher",
            "Weapon Mastery": "Transcendent"
        },
        "Powers": {
            "Power": "Gravity control",
            "Power Mastery": "Omnipotent"
        },
        "Extra": {
            "Weakness": "",
            "Chaos Force": "",
            "Chaos Factor": ""
        },
        "Enchantment": "",
        "Image": "S1 - IRaulLozano.png"
    },
    "Le Onion": {
        "Race": "Goblin",
        "Archetype": "",
        "Role": "Hero",
        "Title": "",
        "Size": "4.5FT",
        "Stats": {
            "Strength": "Superhuman",
            "Speed": "Peak Human",
            "Durability": "Superhuman",
            "IQ": "Prodigious",
            "Fight": "Mid"
        },
        "Weapons": {
            "Weapon": "",
            "Weapon Mastery": "Transcendent"
        },
        "Powers": {
            "Power": "Astral projection",
            "Power Mastery": "Omnipotent"
        },
        "Extra": {
            "Weakness": "",
            "Chaos Force": "",
            "Chaos Factor": ""
        },
        "Enchantment": "",
        "Image": "S1 - Le Onion.png"
    },
    "Argentina": {
        "Race": "Ninja",
        "Archetype": "",
        "Role": "Villain",
        "Title": "",
        "Size": "5FT",
        "Stats": {
            "Strength": "Herculean",
            "Speed": "Superhuman",
            "Durability": "Nuclear",
            "IQ": "Mid",
            "Fight": "Mid"
        },
        "Weapons": {
            "Weapon": "Diamond Sword",
            "Weapon Mastery": "Transcendent"
        },
        "Powers": {
            "Power": "Shadow Cloning",
            "Power Mastery": "Omnipotent"
        },
        "Extra": {
            "Weakness": "",
            "Chaos Force": "",
            "Chaos Factor": ""
        },
        "Enchantment": "",
        "Image": "S1 - Argentina.png"
    },
    "Rachel Webb": {
        "Race": "Mischief God",
        "Archetype": "",
        "Role": "Hero",
        "Title": "",
        "Size": "5FT",
        "Stats": {
            "Strength": "Peak Human",
            "Speed": "Superhuman",
            "Durability": "Nuclear",
            "IQ": "Prodigious",
            "Fight": "Planetary Fighter"
        },
        "Weapons": {
            "Weapon": "Sword",
            "Weapon Mastery": "Transcendent"
        },
        "Powers": {
            "Power": "Summoning + Flying",
            "Power Mastery": "Omnipotent"
        },
        "Extra": {
            "Weakness": "",
            "Chaos Force": "",
            "Chaos Factor": ""
        },
        "Enchantment": "",
        "Image": "S1 - Rachel Webb.png"
    },
    "StreamingJose": {
        "Race": "Werewolf",
        "Archetype": "",
        "Role": "Hero",
        "Title": "",
        "Size": "8.5FT",
        "Stats": {
            "Strength": "Cosmic",
            "Speed": "Superhuman",
            "Durability": "Nuclear",
            "IQ": "Super Genius",
            "Fight": "Cosmic Brawler"
        },
        "Weapons": {
            "Weapon": "Baseball bat",
            "Weapon Mastery": "Transcendent"
        },
        "Powers": {
            "Power": "Reality Warping",
            "Power Mastery": "Omnipotent"
        },
        "Extra": {
            "Weakness": "",
            "Chaos Force": "",
            "Chaos Factor": ""
        },
        "Enchantment": "",
        "Image": "S1 - StreamingJose.png"
    },
    "TrevorCousin": {
        "Race": "Demi God",
        "Archetype": "",
        "Role": "Villain",
        "Title": "",
        "Size": "7FT",
        "Stats": {
            "Strength": "Cosmic",
            "Speed": "Light Speed",
            "Durability": "Mid",
            "IQ": "Prodigious",
            "Fight": "Peak Human"
        },
        "Weapons": {
            "Weapon": "Brass Knuckles",
            "Weapon Mastery": "Transcendent"
        },
        "Powers": {
            "Power": "Fire control + Teleportation",
            "Power Mastery": "Omnipotent"
        },
        "Extra": {
            "Weakness": "",
            "Chaos Force": "",
            "Chaos Factor": ""
        },
        "Enchantment": "",
        "Image": "S1 - TrevorCousin.png"
    },
    "Tobias Villagran": {
        "Race": "Angel",
        "Archetype": "",
        "Role": "Villain",
        "Title": "",
        "Size": "10FT",
        "Stats": {
            "Strength": "Cosmic",
            "Speed": "Superhuman",
            "Durability": "Mid",
            "IQ": "Super Genius",
            "Fight": "Mid"
        },
        "Weapons": {
            "Weapon": "Infinity Gauntlet",
            "Weapon Mastery": "Transcendent"
        },
        "Powers": {
            "Power": "Shockwave",
            "Power Mastery": "Omnipotent"
        },
        "Extra": {
            "Weakness": "",
            "Chaos Force": "",
            "Chaos Factor": ""
        },
        "Enchantment": "",
        "Image": "S1 - Tobias Villagran.png"
    },
    "Austin": {
        "Race": "Alien",
        "Archetype": "",
        "Role": "Villain",
        "Title": "",
        "Size": "8.5FT",
        "Stats": {
            "Strength": "Peak Human",
            "Speed": "Light Speed",
            "Durability": "Nuclear",
            "IQ": "Dumb",
            "Fight": "Darwizzy"
        },
        "Weapons": {
            "Weapon": "Stick",
            "Weapon Mastery": "Transcendent"
        },
        "Powers": {
            "Power": "Invisibility",
            "Power Mastery": "Omnipotent"
        },
        "Extra": {
            "Weakness": "",
            "Chaos Force": "",
            "Chaos Factor": ""
        },
        "Enchantment": "",
        "Image": "S1 - Austin Fitzgerald.png"
    },
    "Mangalox": {
        "Race": "Vampire",
        "Archetype": "",
        "Role": "Hero",
        "Title": "",
        "Size": "6FT",
        "Stats": {
            "Strength": "Herculean",
            "Speed": "Old man",
            "Durability": "Regenerative",
            "IQ": "Genius",
            "Fight": "Peak Human"
        },
        "Weapons": {
            "Weapon": "Hammer",
            "Weapon Mastery": "Transcendent"
        },
        "Powers": {
            "Power": "Sonic Scream",
            "Power Mastery": "Omnipotent"
        },
        "Extra": {
            "Weakness": "",
            "Chaos Force": "",
            "Chaos Factor": ""
        },
        "Enchantment": "",
        "Image": "S1 - Mangalox.png"
    },
    "Cfox": {
        "Race": "Human",
        "Archetype": "",
        "Role": "Villain",
        "Title": "",
        "Size": "6FT",
        "Stats": {
            "Strength": "Herculean",
            "Speed": "Light Speed",
            "Durability": "Cosmic",
            "IQ": "Genius",
            "Fight": "Planetary Fighter"
        },
        "Weapons": {
            "Weapon": "Flamethrower",
            "Weapon Mastery": "Transcendent"
        },
        "Powers": {
            "Power": "Time Travel",
            "Power Mastery": "Omnipotent"
        },
        "Extra": {
            "Weakness": "",
            "Chaos Force": "",
            "Chaos Factor": ""
        },
        "Enchantment": "",
        "Image": "S1 - Cfox.png"
    },
    "Edit": {
        "Race": "Vacuum Robot",
        "Archetype": "",
        "Role": "Villain",
        "Title": "",
        "Size": "10.5FT",
        "Stats": {
            "Strength": "Superhuman",
            "Speed": "Light Speed",
            "Durability": "Cosmic",
            "IQ": "Omniscient",
            "Fight": "Mid"
        },
        "Weapons": {
            "Weapon": "",
            "Weapon Mastery": "Transcendent"
        },
        "Powers": {
            "Power": "Force Field",
            "Power Mastery": "Omnipotent"
        },
        "Extra": {
            "Weakness": "",
            "Chaos Force": "",
            "Chaos Factor": ""
        },
        "Enchantment": "",
        "Image": "S1 - Edit.png"
    },
    "The_Offender": {
        "Race": "Goblin",
        "Archetype": "",
        "Role": "Villain",
        "Title": "",
        "Size": "5FT",
        "Stats": {
            "Strength": "Weak",
            "Speed": "Peak Human",
            "Durability": "Superhuman",
            "IQ": "Prodigious",
            "Fight": "Darwizzy"
        },
        "Weapons": {
            "Weapon": "Infinity Gauntlet",
            "Weapon Mastery": "Transcendent"
        },
        "Powers": {
            "Power": "",
            "Power Mastery": "Omnipotent"
        },
        "Extra": {
            "Weakness": "",
            "Chaos Force": "",
            "Chaos Factor": ""
        },
        "Enchantment": "",
        "Image": "S1 - The_Offender.png"
    },
    "EFT": {
        "Race": "God of Gods",
        "Archetype": "",
        "Role": "Villain",
        "Title": "",
        "Size": "9FT",
        "Stats": {
            "Strength": "Superhuman",
            "Speed": "Light Speed",
            "Durability": "Nuclear",
            "IQ": "Dumb",
            "Fight": "Planetary Fighter"
        },
        "Weapons": {
            "Weapon": "Thor's Hammer",
            "Weapon Mastery": "Transcendent"
        },
        "Powers": {
            "Power": "Reality warping + Shapeshifting + Teleportation + Possessing",
            "Power Mastery": "Omnipotent"
        },
        "Extra": {
            "Weakness": "",
            "Chaos Force": "",
            "Chaos Factor": ""
        },
        "Enchantment": "",
        "Image": "S1 - EFT.png"
    },
    "JustJay": {
        "Race": "Human",
        "Archetype": "",
        "Role": "Villain",
        "Title": "",
        "Size": "7FT",
        "Stats": {
            "Strength": "Weak",
            "Speed": "Light Speed",
            "Durability": "Nuclear",
            "IQ": "Mid",
            "Fight": "Planetary Fighter"
        },
        "Weapons": {
            "Weapon": "",
            "Weapon Mastery": "Transcendent"
        },
        "Powers": {
            "Power": "Fire Control",
            "Power Mastery": "Omnipotent"
        },
        "Extra": {
            "Weakness": "",
            "Chaos Force": "",
            "Chaos Factor": ""
        },
        "Enchantment": "",
        "Image": "S1 - JustJay.png"
    },
    "Nate Torres": {
        "Race": "Fairy",
        "Archetype": "",
        "Role": "Hero",
        "Title": "",
        "Size": "8FT",
        "Stats": {
            "Strength": "Mid",
            "Speed": "Supersonic",
            "Durability": "Darwizzy",
            "IQ": "Prodigious",
            "Fight": "Mid"
        },
        "Weapons": {
            "Weapon": "Rocks",
            "Weapon Mastery": "Transcendent"
        },
        "Powers": {
            "Power": "Healing + Necromancy",
            "Power Mastery": "Omnipotent"
        },
        "Extra": {
            "Weakness": "",
            "Chaos Force": "",
            "Chaos Factor": ""
        },
        "Enchantment": "",
        "Image": "S1 - Nate Torres.png"
    },
    "Ya Boy": {
        "Race": "Alien",
        "Archetype": "",
        "Role": "Hero",
        "Title": "",
        "Size": "5FT",
        "Stats": {
            "Strength": "Superhuman",
            "Speed": "Supersonic",
            "Durability": "Superhuman",
            "IQ": "Omniscient",
            "Fight": "Mid"
        },
        "Weapons": {
            "Weapon": "Excalibur",
            "Weapon Mastery": "Transcendent"
        },
        "Powers": {
            "Power": "Hyper Intelligence",
            "Power Mastery": "Omnipotent"
        },
        "Extra": {
            "Weakness": "",
            "Chaos Force": "",
            "Chaos Factor": ""
        },
        "Enchantment": "",
        "Image": "S1 - Ya Boy.png"
    },
    "Austin Fitzgerald": {
        "Race": "Ninja",
        "Archetype": "",
        "Role": "Hero",
        "Title": "",
        "Size": "6.5FT",
        "Stats": {
            "Strength": "Herculean",
            "Speed": "Superhuman",
            "Durability": "Superhuman",
            "IQ": "Dumb",
            "Fight": "Amateur"
        },
        "Weapons": {
            "Weapon": "Excalibur",
            "Weapon Mastery": "Transcendent"
        },
        "Powers": {
            "Power": "Rasengan",
            "Power Mastery": "Omnipotent"
        },
        "Extra": {
            "Weakness": "",
            "Chaos Force": "",
            "Chaos Factor": ""
        },
        "Enchantment": "",
        "Image": "S1 - Austin Fitzgerald.png"
    },
    "VeryNiceLikeLMush": {
        "Race": "Demi God",
        "Archetype": "",
        "Role": "Villain",
        "Title": "",
        "Size": "10FT",
        "Stats": {
            "Strength": "Herculean",
            "Speed": "Supersonic",
            "Durability": "Nuclear",
            "IQ": "Genius",
            "Fight": "Cosmic Brawler"
        },
        "Weapons": {
            "Weapon": "Brass Knuckles",
            "Weapon Mastery": "Transcendent"
        },
        "Powers": {
            "Power": "Water Control",
            "Power Mastery": "Omnipotent"
        },
        "Extra": {
            "Weakness": "",
            "Chaos Force": "",
            "Chaos Factor": ""
        },
        "Enchantment": "",
        "Image": "S1 - VeryNiceLikeLMush.png"
    },
    "The Big Squish": {
        "Race": "Human",
        "Archetype": "",
        "Role": "Villain",
        "Title": "",
        "Size": "10FT",
        "Stats": {
            "Strength": "Weak",
            "Speed": "Old man",
            "Durability": "Mid",
            "IQ": "Dumb",
            "Fight": "Darwizzy"
        },
        "Weapons": {
            "Weapon": "BlowGun",
            "Weapon Mastery": "Transcendent"
        },
        "Powers": {
            "Power": "Water Control",
            "Power Mastery": "Omnipotent"
        },
        "Extra": {
            "Weakness": "",
            "Chaos Force": "",
            "Chaos Factor": ""
        },
        "Enchantment": "",
        "Image": "S1 - The Big Squish.png"
    },
    "Liniticii": {
        "Race": "Angel",
        "Archetype": "",
        "Role": "Hero",
        "Title": "",
        "Size": "7FT",
        "Stats": {
            "Strength": "Peak Human",
            "Speed": "Light Speed",
            "Durability": "Darwizzy",
            "IQ": "Omniscient",
            "Fight": "Mid"
        },
        "Weapons": {
            "Weapon": "",
            "Weapon Mastery": "Transcendent"
        },
        "Powers": {
            "Power": "Water Breathing",
            "Power Mastery": "Omnipotent"
        },
        "Extra": {
            "Weakness": "",
            "Chaos Force": "",
            "Chaos Factor": ""
        },
        "Enchantment": "",
        "Image": "S1 - Liniticii.png"
    },
    "Phoenix": {
        "Race": "Goblin",
        "Archetype": "",
        "Role": "Villain",
        "Title": "",
        "Size": "8FT",
        "Stats": {
            "Strength": "Mid",
            "Speed": "Light Speed",
            "Durability": "Darwizzy",
            "IQ": "Mid",
            "Fight": "Amateur"
        },
        "Weapons": {
            "Weapon": "Diamond Sword",
            "Weapon Mastery": "Transcendent"
        },
        "Powers": {
            "Power": "Animal Control",
            "Power Mastery": "Omnipotent"
        },
        "Extra": {
            "Weakness": "",
            "Chaos Force": "",
            "Chaos Factor": ""
        },
        "Enchantment": "",
        "Image": "S1 - Phoenix.png"
    },
    "TevinHicks": {
        "Race": "Vampire",
        "Archetype": "",
        "Role": "Villain",
        "Title": "",
        "Size": "5FT",
        "Stats": {
            "Strength": "Peak Human",
            "Speed": "Supersonic",
            "Durability": "Mid",
            "IQ": "Super Genius",
            "Fight": "Cosmic Brawler"
        },
        "Weapons": {
            "Weapon": "",
            "Weapon Mastery": "Transcendent"
        },
        "Powers": {
            "Power": "Heat Vision",
            "Power Mastery": "Omnipotent"
        },
        "Extra": {
            "Weakness": "",
            "Chaos Force": "",
            "Chaos Factor": ""
        },
        "Enchantment": "",
        "Image": "S2 - TevinHicks.png"
    },
    "HunterS": {
        "Race": "Ninja",
        "Archetype": "",
        "Role": "Hero",
        "Title": "",
        "Size": "4.5FT",
        "Stats": {
            "Strength": "Peak Human",
            "Speed": "Supersonic",
            "Durability": "Regenerative",
            "IQ": "Prodigious",
            "Fight": "Mid"
        },
        "Weapons": {
            "Weapon": "Baseball bat",
            "Weapon Mastery": "Transcendent"
        },
        "Powers": {
            "Power": "Fireball",
            "Power Mastery": "Omnipotent"
        },
        "Extra": {
            "Weakness": "",
            "Chaos Force": "",
            "Chaos Factor": ""
        },
        "Enchantment": "",
        "Image": "S1 - HunterS.png"
    },
    "Kalenstecz": {
        "Race": "Werewolf",
        "Archetype": "",
        "Role": "Hero",
        "Title": "",
        "Size": "4FT",
        "Stats": {
            "Strength": "Herculean",
            "Speed": "Peak Human",
            "Durability": "Nuclear",
            "IQ": "Prodigious",
            "Fight": "Mid"
        },
        "Weapons": {
            "Weapon": "Captain Shield",
            "Weapon Mastery": "Transcendent"
        },
        "Powers": {
            "Power": "Intangibility",
            "Power Mastery": "Omnipotent"
        },
        "Extra": {
            "Weakness": "",
            "Chaos Force": "",
            "Chaos Factor": ""
        },
        "Enchantment": "",
        "Image": "S1 - Kalenstecz.png"
    },
    "Ultratie": {
        "Race": "Alien",
        "Archetype": "",
        "Role": "Villain",
        "Title": "",
        "Size": "4.5FT",
        "Stats": {
            "Strength": "Peak Human",
            "Speed": "Peak Human",
            "Durability": "Nuclear",
            "IQ": "Mid",
            "Fight": "Unbeatable"
        },
        "Weapons": {
            "Weapon": "Brass Knuckles",
            "Weapon Mastery": "Transcendent"
        },
        "Powers": {
            "Power": "Flying",
            "Power Mastery": "Omnipotent"
        },
        "Extra": {
            "Weakness": "",
            "Chaos Force": "",
            "Chaos Factor": ""
        },
        "Enchantment": "",
        "Image": "S1 - Ultratie.png"
    },
    "CertifiedMobboss": {
        "Race": "Underworld God",
        "Archetype": "",
        "Role": "Villain",
        "Title": "",
        "Size": "10.5FT",
        "Stats": {
            "Strength": "Herculean",
            "Speed": "Light Speed",
            "Durability": "Mid",
            "IQ": "Prodigious",
            "Fight": "Planetary Fighter"
        },
        "Weapons": {
            "Weapon": "",
            "Weapon Mastery": "Transcendent"
        },
        "Powers": {
            "Power": "Force Field + Gravity Control",
            "Power Mastery": "Omnipotent"
        },
        "Extra": {
            "Weakness": "",
            "Chaos Force": "",
            "Chaos Factor": ""
        },
        "Enchantment": "",
        "Image": "S1 - CertifiedMobboss.png"
    },
    "ItsMitchyyeah": {
        "Race": "Demi God",
        "Archetype": "",
        "Role": "Villain",
        "Title": "",
        "Size": "6.5FT",
        "Stats": {
            "Strength": "Herculean",
            "Speed": "Supersonic",
            "Durability": "Mid",
            "IQ": "Super Genius",
            "Fight": "Planetary Fighter"
        },
        "Weapons": {
            "Weapon": "Wolverine Claws",
            "Weapon Mastery": "Transcendent"
        },
        "Powers": {
            "Power": "Reality Warping",
            "Power Mastery": "Omnipotent"
        },
        "Extra": {
            "Weakness": "",
            "Chaos Force": "",
            "Chaos Factor": ""
        },
        "Enchantment": "",
        "Image": "S1 - ItsMitchyyeah.png"
    },
    "Dansemacabre": {
        "Race": "Fairy",
        "Archetype": "",
        "Role": "Villain",
        "Title": "",
        "Size": "8FT",
        "Stats": {
            "Strength": "Mid",
            "Speed": "Old man",
            "Durability": "Regenerative",
            "IQ": "Dumb",
            "Fight": "Planetary Fighter"
        },
        "Weapons": {
            "Weapon": "",
            "Weapon Mastery": "Transcendent"
        },
        "Powers": {
            "Power": "Flying + Healing",
            "Power Mastery": "Omnipotent"
        },
        "Extra": {
            "Weakness": "",
            "Chaos Force": "",
            "Chaos Factor": ""
        },
        "Enchantment": "",
        "Image": "S1 - Dansemacabre.png"
    },
    "Jekixoxo": {
        "Race": "Angel",
        "Archetype": "",
        "Role": "Hero",
        "Title": "",
        "Size": "10.5FT",
        "Stats": {
            "Strength": "Cosmic",
            "Speed": "Light Speed",
            "Durability": "Cosmic",
            "IQ": "Prodigious",
            "Fight": "Planetary Fighter"
        },
        "Weapons": {
            "Weapon": "Excalibur",
            "Weapon Mastery": "Transcendent"
        },
        "Powers": {
            "Power": "Power counter",
            "Power Mastery": "Omnipotent"
        },
        "Extra": {
            "Weakness": "",
            "Chaos Force": "",
            "Chaos Factor": ""
        },
        "Enchantment": "",
        "Image": "S1 - Jekixoxo.png"
    },
    "Infernob1rdo": {
        "Race": "Vacuum Robot",
        "Archetype": "",
        "Role": "Villain",
        "Title": "",
        "Size": "7.5FT",
        "Stats": {
            "Strength": "Cosmic",
            "Speed": "Superhuman",
            "Durability": "Nuclear",
            "IQ": "Mid",
            "Fight": "Mid"
        },
        "Weapons": {
            "Weapon": "",
            "Weapon Mastery": "Transcendent"
        },
        "Powers": {
            "Power": "Teleportation",
            "Power Mastery": "Omnipotent"
        },
        "Extra": {
            "Weakness": "",
            "Chaos Force": "",
            "Chaos Factor": ""
        },
        "Enchantment": "",
        "Image": "S1 - Infernob1rdo.png"
    },
    "Echo": {
        "Race": "Ninja",
        "Archetype": "",
        "Role": "Villain",
        "Title": "",
        "Size": "4FT",
        "Stats": {
            "Strength": "Cosmic",
            "Speed": "Mid",
            "Durability": "Regenerative",
            "IQ": "Prodigious",
            "Fight": "Planetary Fighter"
        },
        "Weapons": {
            "Weapon": "Ukulele",
            "Weapon Mastery": "Transcendent"
        },
        "Powers": {
            "Power": "Amaterasu + Poison fist",
            "Power Mastery": "Omnipotent"
        },
        "Extra": {
            "Weakness": "",
            "Chaos Force": "",
            "Chaos Factor": ""
        },
        "Enchantment": "",
        "Image": "S1 - Echo.png"
    },
    "Fuegowave": {
        "Race": "Demi God",
        "Archetype": "",
        "Role": "Hero",
        "Title": "",
        "Size": "5FT",
        "Stats": {
            "Strength": "Cosmic",
            "Speed": "Superhuman",
            "Durability": "Nuclear",
            "IQ": "Prodigious",
            "Fight": "Mid"
        },
        "Weapons": {
            "Weapon": "Wolverine Claws",
            "Weapon Mastery": "Transcendent"
        },
        "Powers": {
            "Power": "Fire control + Elasticity",
            "Power Mastery": "Omnipotent"
        },
        "Extra": {
            "Weakness": "",
            "Chaos Force": "",
            "Chaos Factor": ""
        },
        "Enchantment": "",
        "Image": "S1 - Fuegowave.png"
    },
    "Personalborderline": {
        "Race": "Love God",
        "Archetype": "",
        "Role": "Hero",
        "Title": "",
        "Size": "8.5FT",
        "Stats": {
            "Strength": "Peak Human",
            "Speed": "Old man",
            "Durability": "Mid",
            "IQ": "Super Genius",
            "Fight": "Planetary Fighter"
        },
        "Weapons": {
            "Weapon": "Bow",
            "Weapon Mastery": "Transcendent"
        },
        "Powers": {
            "Power": "Time Travel",
            "Power Mastery": "Omnipotent"
        },
        "Extra": {
            "Weakness": "",
            "Chaos Force": "",
            "Chaos Factor": ""
        },
        "Enchantment": "",
        "Image": "S1 - Personalborderline.png"
    },
    "ISwearImNotHacking": {
        "Race": "Werewolf",
        "Archetype": "",
        "Role": "Villain",
        "Title": "",
        "Size": "7FT",
        "Stats": {
            "Strength": "Peak Human",
            "Speed": "Superhuman",
            "Durability": "Mid",
            "IQ": "Dumb",
            "Fight": "Planetary Fighter"
        },
        "Weapons": {
            "Weapon": "",
            "Weapon Mastery": "Transcendent"
        },
        "Powers": {
            "Power": "Necromancy",
            "Power Mastery": "Omnipotent"
        },
        "Extra": {
            "Weakness": "",
            "Chaos Force": "",
            "Chaos Factor": ""
        },
        "Enchantment": "",
        "Image": "S1 - ISwearImNotHacking.png"
    },
    "1_torri_sin": {
        "Race": "Robot",
        "Archetype": "",
        "Role": "Villain",
        "Title": "",
        "Size": "5FT",
        "Stats": {
            "Strength": "Cosmic",
            "Speed": "Old man",
            "Durability": "Nuclear",
            "IQ": "Genius",
            "Fight": "Amateur"
        },
        "Weapons": {
            "Weapon": "Grenade Launcher",
            "Weapon Mastery": "Transcendent"
        },
        "Powers": {
            "Power": "",
            "Power Mastery": "Omnipotent"
        },
        "Extra": {
            "Weakness": "",
            "Chaos Force": "",
            "Chaos Factor": ""
        },
        "Enchantment": "",
        "Image": "S1 - 1_torri_sin.png"
    },
    "Gijoe": {
        "Race": "Alien",
        "Archetype": "",
        "Role": "Hero",
        "Title": "",
        "Size": "8.5FT",
        "Stats": {
            "Strength": "Weak",
            "Speed": "Mid",
            "Durability": "Superhuman",
            "IQ": "Dumb",
            "Fight": "Mid"
        },
        "Weapons": {
            "Weapon": "Sniper",
            "Weapon Mastery": "Transcendent"
        },
        "Powers": {
            "Power": "Mind Reading + Superman",
            "Power Mastery": "Omnipotent"
        },
        "Extra": {
            "Weakness": "",
            "Chaos Force": "",
            "Chaos Factor": ""
        },
        "Enchantment": "",
        "Image": "S1 - Gijoe.png"
    },
    "The Johnny Boy": {
        "Race": "Demi God",
        "Archetype": "",
        "Role": "Anti-Hero",
        "Title": "",
        "Size": "6FT",
        "Stats": {
            "Strength": "Superhuman",
            "Speed": "Peak Human",
            "Durability": "Darwizzy",
            "IQ": "Prodigious",
            "Fight": "Darwizzy"
        },
        "Weapons": {
            "Weapon": "Whip",
            "Weapon Mastery": "Transcendent"
        },
        "Powers": {
            "Power": "Thunder control",
            "Power Mastery": "Omnipotent"
        },
        "Extra": {
            "Weakness": "",
            "Chaos Force": "",
            "Chaos Factor": ""
        },
        "Enchantment": "",
        "Image": "S1 - The Johnny Boy.png"
    },
    "Theofficialaydan": {
        "Race": "Angel",
        "Archetype": "",
        "Role": "Hero",
        "Title": "",
        "Size": "6FT",
        "Stats": {
            "Strength": "Herculean",
            "Speed": "Light Speed",
            "Durability": "Cosmic",
            "IQ": "Omniscient",
            "Fight": "Darwizzy"
        },
        "Weapons": {
            "Weapon": "",
            "Weapon Mastery": "Transcendent"
        },
        "Powers": {
            "Power": "Mind Reading",
            "Power Mastery": "Omnipotent"
        },
        "Extra": {
            "Weakness": "",
            "Chaos Force": "",
            "Chaos Factor": ""
        },
        "Enchantment": "",
        "Image": "S1 - Theofficialaydan.png"
    },
    "yerboibaron": {
        "Race": "Dragon",
        "Archetype": "",
        "Role": "?",
        "Title": "",
        "Size": "30FT",
        "Stats": {
            "Strength": "Superhuman",
            "Speed": "Old man",
            "Durability": "Nuclear",
            "IQ": "Genius",
            "Fight": "Darwizzy"
        },
        "Weapons": {
            "Weapon": "",
            "Weapon Mastery": "Transcendent"
        },
        "Powers": {
            "Power": "Invisibility + Shadow control + Bone control",
            "Power Mastery": "Omnipotent"
        },
        "Extra": {
            "Weakness": "",
            "Chaos Force": "",
            "Chaos Factor": ""
        },
        "Enchantment": "",
        "Image": "S1 - yerboibaron.png"
    },
    "Rinklepopple": {
        "Race": "Demon",
        "Archetype": "",
        "Role": "?",
        "Title": "",
        "Size": "7FT",
        "Stats": {
            "Strength": "Superhuman",
            "Speed": "Old man",
            "Durability": "Nuclear",
            "IQ": "Nigh-Omniscience",
            "Fight": "Meta-Martial"
        },
        "Weapons": {
            "Weapon": "Blades of Chaos",
            "Weapon Mastery": "Transcendent"
        },
        "Powers": {
            "Power": "Paralysis",
            "Power Mastery": "Omnipotent"
        },
        "Extra": {
            "Weakness": "",
            "Chaos Force": "",
            "Chaos Factor": ""
        },
        "Enchantment": "",
        "Image": "S1 - Rinklepopple.png"
    },
    "Maverickjugg": {
        "Race": "Skeleton",
        "Archetype": "",
        "Role": "?",
        "Title": "",
        "Size": "11FT",
        "Stats": {
            "Strength": "Weak",
            "Speed": "Old man",
            "Durability": "Mid",
            "IQ": "Prodigious",
            "Fight": "Mid"
        },
        "Weapons": {
            "Weapon": "Diamond Sword",
            "Weapon Mastery": "Transcendent"
        },
        "Powers": {
            "Power": "Sarcastic Humor",
            "Power Mastery": "Omnipotent"
        },
        "Extra": {
            "Weakness": "",
            "Chaos Force": "",
            "Chaos Factor": ""
        },
        "Enchantment": "",
        "Image": "S1 - Maverickjugg.png"
    },
    "Redpans": {
        "Race": "Elf",
        "Archetype": "",
        "Role": "?",
        "Title": "",
        "Size": "4.5FT",
        "Stats": {
            "Strength": "Herculean",
            "Speed": "Light Speed",
            "Durability": "Nuclear",
            "IQ": "Prodigious",
            "Fight": "Mid"
        },
        "Weapons": {
            "Weapon": "Green lanter ring",
            "Weapon Mastery": "Transcendent"
        },
        "Powers": {
            "Power": "Phasing + Rizz",
            "Power Mastery": "Omnipotent"
        },
        "Extra": {
            "Weakness": "",
            "Chaos Force": "",
            "Chaos Factor": ""
        },
        "Enchantment": "",
        "Image": "S1 - Redpans.png"
    },
    "Thedailyvibe": {
        "Race": "Giant",
        "Archetype": "",
        "Role": "?",
        "Title": "",
        "Size": "16FT",
        "Stats": {
            "Strength": "Herculean",
            "Speed": "Old man",
            "Durability": "Nuclear",
            "IQ": "Mid",
            "Fight": "Unbeatable"
        },
        "Weapons": {
            "Weapon": "Light saber",
            "Weapon Mastery": "Transcendent"
        },
        "Powers": {
            "Power": "Colossal ass stomp",
            "Power Mastery": "Omnipotent"
        },
        "Extra": {
            "Weakness": "",
            "Chaos Force": "",
            "Chaos Factor": ""
        },
        "Enchantment": "",
        "Image": "S1 - Thedailyvibe.png"
    },
    "Cwes": {
        "Race": "Cosmic Warrior",
        "Archetype": "",
        "Role": "?",
        "Title": "",
        "Size": "4.5FT",
        "Stats": {
            "Strength": "Boundless",
            "Speed": "Supersonic",
            "Durability": "Nuclear",
            "IQ": "Dumb",
            "Fight": "Unbeatable"
        },
        "Weapons": {
            "Weapon": "",
            "Weapon Mastery": "Transcendent"
        },
        "Powers": {
            "Power": "Extreme reflexes + Invulnerability",
            "Power Mastery": "Omnipotent"
        },
        "Extra": {
            "Weakness": "",
            "Chaos Force": "",
            "Chaos Factor": ""
        },
        "Enchantment": "",
        "Image": "S1 - Cwes.png"
    },
    "Luciferhellfirex": {
        "Race": "Light God",
        "Archetype": "",
        "Role": "?",
        "Title": "",
        "Size": "7FT",
        "Stats": {
            "Strength": "Mid",
            "Speed": "Light Speed",
            "Durability": "Durability",
            "IQ": "Omniscient",
            "Fight": "Planetary Fighter"
        },
        "Weapons": {
            "Weapon": "Boomerang",
            "Weapon Mastery": "Transcendent"
        },
        "Powers": {
            "Power": "Light + time manipulation + Teleportation",
            "Power Mastery": "Omnipotent"
        },
        "Extra": {
            "Weakness": "",
            "Chaos Force": "",
            "Chaos Factor": ""
        },
        "Enchantment": "",
        "Image": "S1 - Luciferhellfirex.png"
    },
    "Spency": {
        "Race": "Dragon",
        "Archetype": "",
        "Role": "?",
        "Title": "",
        "Size": "30FT",
        "Stats": {
            "Strength": "Weak",
            "Speed": "Old man",
            "Durability": "Cosmic",
            "IQ": "Prodigious",
            "Fight": "Darwizzy"
        },
        "Weapons": {
            "Weapon": "Zeus thunderbolt",
            "Weapon Mastery": "Transcendent"
        },
        "Powers": {
            "Power": "Thunder control",
            "Power Mastery": "Omnipotent"
        },
        "Extra": {
            "Weakness": "",
            "Chaos Force": "",
            "Chaos Factor": ""
        },
        "Enchantment": "",
        "Image": "S1 - Spency.png"
    },
    "Michael": {
        "Race": "Werewolf",
        "Archetype": "",
        "Role": "?",
        "Title": "",
        "Size": "11FT",
        "Stats": {
            "Strength": "Superhuman",
            "Speed": "Supersonic",
            "Durability": "Nuclear",
            "IQ": "Dumb",
            "Fight": "Universal Gladiator"
        },
        "Weapons": {
            "Weapon": "",
            "Weapon Mastery": "Transcendent"
        },
        "Powers": {
            "Power": "Berserker",
            "Power Mastery": "Omnipotent"
        },
        "Extra": {
            "Weakness": "",
            "Chaos Force": "",
            "Chaos Factor": ""
        },
        "Enchantment": "",
        "Image": "S1 - Michael.png"
    },
    "Philgood": {
        "Race": "Zombie",
        "Archetype": "",
        "Role": "?",
        "Title": "",
        "Size": "4.5FT",
        "Stats": {
            "Strength": "Peak Human",
            "Speed": "Old man",
            "Durability": "Nuclear",
            "IQ": "Nigh-Omniscience",
            "Fight": "Mid"
        },
        "Weapons": {
            "Weapon": "Flamethrower",
            "Weapon Mastery": "Transcendent"
        },
        "Powers": {
            "Power": "",
            "Power Mastery": "Omnipotent"
        },
        "Extra": {
            "Weakness": "",
            "Chaos Force": "",
            "Chaos Factor": ""
        },
        "Enchantment": "",
        "Image": "S1 - Philgood.png"
    },
    "Shadowzerox": {
        "Race": "Demi God",
        "Archetype": "",
        "Role": "?",
        "Title": "",
        "Size": "8FT",
        "Stats": {
            "Strength": "Herculean",
            "Speed": "Mid",
            "Durability": "Nuclear",
            "IQ": "Dumb",
            "Fight": "Darwizzy"
        },
        "Weapons": {
            "Weapon": "",
            "Weapon Mastery": "Transcendent"
        },
        "Powers": {
            "Power": "All elementals",
            "Power Mastery": "Omnipotent"
        },
        "Extra": {
            "Weakness": "",
            "Chaos Force": "",
            "Chaos Factor": ""
        },
        "Enchantment": "",
        "Image": "S1 - Shadowzerox.png"
    },
    "TheGodoftaco": {
        "Race": "Human",
        "Archetype": "",
        "Role": "?",
        "Title": "",
        "Size": "4FT",
        "Stats": {
            "Strength": "Mid",
            "Speed": "Supersonic",
            "Durability": "Nuclear",
            "IQ": "Prodigious",
            "Fight": "Meta-Martial"
        },
        "Weapons": {
            "Weapon": "Wolverine Claws",
            "Weapon Mastery": "Transcendent"
        },
        "Powers": {
            "Power": "Time travel",
            "Power Mastery": "Omnipotent"
        },
        "Extra": {
            "Weakness": "",
            "Chaos Force": "",
            "Chaos Factor": ""
        },
        "Enchantment": "",
        "Image": "S1 - TheGodoftaco.png"
    },
    "Firelightmystic": {
        "Race": "Goblin",
        "Archetype": "",
        "Role": "?",
        "Title": "",
        "Size": "9.5FT",
        "Stats": {
            "Strength": "Superhuman",
            "Speed": "Supersonic",
            "Durability": "Nuclear",
            "IQ": "Dumb",
            "Fight": "Champion"
        },
        "Weapons": {
            "Weapon": "Halberd",
            "Weapon Mastery": "Transcendent"
        },
        "Powers": {
            "Power": "Power absorption + thunder control",
            "Power Mastery": "Omnipotent"
        },
        "Extra": {
            "Weakness": "",
            "Chaos Force": "",
            "Chaos Factor": ""
        },
        "Enchantment": "",
        "Image": "S1 - Firelightmystic.png"
    },
    "Jlap.edits": {
        "Race": "Elf",
        "Archetype": "",
        "Role": "?",
        "Title": "",
        "Size": "6.5FT",
        "Stats": {
            "Strength": "Weak",
            "Speed": "Superhuman",
            "Durability": "Nuclear",
            "IQ": "Nigh-Omniscience",
            "Fight": "Meta-Martial"
        },
        "Weapons": {
            "Weapon": "Thor's Hammer",
            "Weapon Mastery": "Transcendent"
        },
        "Powers": {
            "Power": "Infinite Rizz",
            "Power Mastery": "Omnipotent"
        },
        "Extra": {
            "Weakness": "",
            "Chaos Force": "",
            "Chaos Factor": ""
        },
        "Enchantment": "",
        "Image": "S1 - Jlap.edits.png"
    },
    "Griffin.btw": {
        "Race": "Hybrid",
        "Archetype": "",
        "Role": "?",
        "Title": "",
        "Size": "14.5FT",
        "Stats": {
            "Strength": "Superhuman",
            "Speed": "Light Speed",
            "Durability": "Superhuman",
            "IQ": "Prodigious",
            "Fight": "Meta-Martial"
        },
        "Weapons": {
            "Weapon": "Stick",
            "Weapon Mastery": "Transcendent"
        },
        "Powers": {
            "Power": "Primordial Anihilation + Earthquake -Toon force",
            "Power Mastery": "Omnipotent"
        },
        "Extra": {
            "Weakness": "",
            "Chaos Force": "",
            "Chaos Factor": ""
        },
        "Enchantment": "",
        "Image": "S1 - Griffin.btw.png"
    },
    "Gildarshbutiktok": {
        "Race": "Robot",
        "Archetype": "",
        "Role": "?",
        "Title": "",
        "Size": "7FT",
        "Stats": {
            "Strength": "Cosmic",
            "Speed": "Light Speed",
            "Durability": "Cosmic",
            "IQ": "Dumb",
            "Fight": "Mid"
        },
        "Weapons": {
            "Weapon": "Sonic Blaster -Green lanter ring",
            "Weapon Mastery": "Transcendent"
        },
        "Powers": {
            "Power": "",
            "Power Mastery": "Omnipotent"
        },
        "Extra": {
            "Weakness": "",
            "Chaos Force": "",
            "Chaos Factor": ""
        },
        "Enchantment": "",
        "Image": "S1 - Gildarshbutiktok.png"
    },
    "Jeffnightfall": {
        "Race": "Vampire",
        "Archetype": "",
        "Role": "?",
        "Title": "",
        "Size": "4FT",
        "Stats": {
            "Strength": "Peak Human",
            "Speed": "Mid",
            "Durability": "Nuclear",
            "IQ": "Genius",
            "Fight": "Mid"
        },
        "Weapons": {
            "Weapon": "Ukulele",
            "Weapon Mastery": "Transcendent"
        },
        "Powers": {
            "Power": "Phasing + Water breathing",
            "Power Mastery": "Omnipotent"
        },
        "Extra": {
            "Weakness": "",
            "Chaos Force": "",
            "Chaos Factor": ""
        },
        "Enchantment": "",
        "Image": "S1 - Jeffnightfall.png"
    },
    "Geclipse": {
        "Race": "Cosmic Warrior",
        "Archetype": "",
        "Role": "?",
        "Title": "",
        "Size": "7FT",
        "Stats": {
            "Strength": "Boundless +1",
            "Speed": "Superhuman",
            "Durability": "Regenerative",
            "IQ": "Genius",
            "Fight": "Mid"
        },
        "Weapons": {
            "Weapon": "",
            "Weapon Mastery": "Transcendent"
        },
        "Powers": {
            "Power": "Resurrection",
            "Power Mastery": "Omnipotent"
        },
        "Extra": {
            "Weakness": "",
            "Chaos Force": "",
            "Chaos Factor": ""
        },
        "Enchantment": "",
        "Image": "S1 - Geclipse.png"
    },
    "Titaniumknight": {
        "Race": "Angel",
        "Archetype": "",
        "Role": "?",
        "Title": "",
        "Size": "10.5FT",
        "Stats": {
            "Strength": "Superhuman",
            "Speed": "Old man",
            "Durability": "Cosmic",
            "IQ": "Dumb",
            "Fight": "Planetary Fighter"
        },
        "Weapons": {
            "Weapon": "",
            "Weapon Mastery": "Transcendent"
        },
        "Powers": {
            "Power": "Cosmic Energy + Power absorption",
            "Power Mastery": "Omnipotent"
        },
        "Extra": {
            "Weakness": "",
            "Chaos Force": "",
            "Chaos Factor": ""
        },
        "Enchantment": "",
        "Image": "S1 - Titaniumknight.png"
    },
    "Big_lo": {
        "Race": "Alien",
        "Archetype": "",
        "Role": "?",
        "Title": "",
        "Size": "10FT",
        "Stats": {
            "Strength": "Weak",
            "Speed": "Old man",
            "Durability": "Nuclear",
            "IQ": "Genius",
            "Fight": "Darwizzy"
        },
        "Weapons": {
            "Weapon": "Dagger of time",
            "Weapon Mastery": "Transcendent"
        },
        "Powers": {
            "Power": "Invisibility + Sonic Scream",
            "Power Mastery": "Omnipotent"
        },
        "Extra": {
            "Weakness": "",
            "Chaos Force": "",
            "Chaos Factor": ""
        },
        "Enchantment": "",
        "Image": "S1 - Big_lo.png"
    },
    "N00ner": {
        "Race": "Justice God",
        "Archetype": "",
        "Role": "?",
        "Title": "",
        "Size": "7.5FT",
        "Stats": {
            "Strength": "Herculean",
            "Speed": "Light Speed",
            "Durability": "Cosmic",
            "IQ": "Genius",
            "Fight": "Universal Gladiator"
        },
        "Weapons": {
            "Weapon": "Sword",
            "Weapon Mastery": "Transcendent"
        },
        "Powers": {
            "Power": "Reality influence + invisibility",
            "Power Mastery": "Omnipotent"
        },
        "Extra": {
            "Weakness": "",
            "Chaos Force": "",
            "Chaos Factor": ""
        },
        "Enchantment": "",
        "Image": "S1 - N00ner.png"
    },
    "Road_Zombie": {
        "Race": "Human",
        "Archetype": "",
        "Role": "?",
        "Title": "",
        "Size": "7.5FT",
        "Stats": {
            "Strength": "Cosmic",
            "Speed": "Superhuman",
            "Durability": "Nuclear",
            "IQ": "Prodigious",
            "Fight": "Darwizzy"
        },
        "Weapons": {
            "Weapon": "Diamond Sword",
            "Weapon Mastery": "Transcendent"
        },
        "Powers": {
            "Power": "Rizz",
            "Power Mastery": "Omnipotent"
        },
        "Extra": {
            "Weakness": "",
            "Chaos Force": "",
            "Chaos Factor": ""
        },
        "Enchantment": "",
        "Image": "S1 - Road_Zombie.png"
    },
    "Sio0tz": {
        "Race": "Hybrid",
        "Archetype": "",
        "Role": "?",
        "Title": "",
        "Size": "6FT",
        "Stats": {
            "Strength": "Superhuman",
            "Speed": "Light Speed",
            "Durability": "Cosmic",
            "IQ": "Genius",
            "Fight": "Meta-Martial"
        },
        "Weapons": {
            "Weapon": "",
            "Weapon Mastery": "Transcendent"
        },
        "Powers": {
            "Power": "Fire control + Molecular Manipulation",
            "Power Mastery": "Omnipotent"
        },
        "Extra": {
            "Weakness": "",
            "Chaos Force": "",
            "Chaos Factor": ""
        },
        "Enchantment": "",
        "Image": "S1 - Sio0tz.png"
    },
    "Darwizzy_ii": {
        "Race": "Dragon",
        "Archetype": "",
        "Role": "?",
        "Title": "",
        "Size": "30FT",
        "Stats": {
            "Strength": "Weak",
            "Speed": "Peak Human",
            "Durability": "Darwizzy",
            "IQ": "Nigh-Omniscience",
            "Fight": "Mid"
        },
        "Weapons": {
            "Weapon": "Sniper",
            "Weapon Mastery": "Transcendent"
        },
        "Powers": {
            "Power": "Ice control",
            "Power Mastery": "Omnipotent"
        },
        "Extra": {
            "Weakness": "",
            "Chaos Force": "",
            "Chaos Factor": ""
        },
        "Enchantment": "",
        "Image": "S1 - Darwizzy_ii.png"
    },
    "Reaperx": {
        "Race": "Elf",
        "Archetype": "",
        "Role": "?",
        "Title": "",
        "Size": "5FT",
        "Stats": {
            "Strength": "Herculean",
            "Speed": "Superhuman",
            "Durability": "Darwizzy",
            "IQ": "Prodigious",
            "Fight": "Meta-Martial"
        },
        "Weapons": {
            "Weapon": "",
            "Weapon Mastery": "Transcendent"
        },
        "Powers": {
            "Power": "infinite Rizz",
            "Power Mastery": "Omnipotent"
        },
        "Extra": {
            "Weakness": "",
            "Chaos Force": "",
            "Chaos Factor": ""
        },
        "Enchantment": "",
        "Image": "S1 - Reaperx.png"
    },
    "Tbpmatt": {
        "Race": "Vampire",
        "Archetype": "",
        "Role": "?",
        "Title": "",
        "Size": "8.5FT",
        "Stats": {
            "Strength": "Boundless",
            "Speed": "Light Speed",
            "Durability": "Regenerative",
            "IQ": "Genius",
            "Fight": "Meta-Martial"
        },
        "Weapons": {
            "Weapon": "Rocks",
            "Weapon Mastery": "Transcendent"
        },
        "Powers": {
            "Power": "Soul absorption",
            "Power Mastery": "Omnipotent"
        },
        "Extra": {
            "Weakness": "",
            "Chaos Force": "",
            "Chaos Factor": ""
        },
        "Enchantment": "",
        "Image": "S1 - Tbpmatt.png"
    },
    "Greekgodoftheseas": {
        "Race": "Goblin",
        "Archetype": "",
        "Role": "?",
        "Title": "",
        "Size": "9FT",
        "Stats": {
            "Strength": "Mid",
            "Speed": "Peak Human",
            "Durability": "Mid",
            "IQ": "Mid",
            "Fight": "Darwizzy"
        },
        "Weapons": {
            "Weapon": "",
            "Weapon Mastery": "Transcendent"
        },
        "Powers": {
            "Power": "Darwizzy",
            "Power Mastery": "Omnipotent"
        },
        "Extra": {
            "Weakness": "",
            "Chaos Force": "",
            "Chaos Factor": ""
        },
        "Enchantment": "",
        "Image": "S1 - Greekgodoftheseas.png"
    },
    "Midlysavage": {
        "Race": "Demon",
        "Archetype": "",
        "Role": "?",
        "Title": "",
        "Size": "7FT",
        "Stats": {
            "Strength": "Herculean",
            "Speed": "Supersonic",
            "Durability": "Nuclear",
            "IQ": "Prodigious",
            "Fight": "Planetary Fighter"
        },
        "Weapons": {
            "Weapon": "Bow of Apollo",
            "Weapon Mastery": "Transcendent"
        },
        "Powers": {
            "Power": "Paradoxial Chaos + Tough skin",
            "Power Mastery": "Omnipotent"
        },
        "Extra": {
            "Weakness": "",
            "Chaos Force": "",
            "Chaos Factor": ""
        },
        "Enchantment": "",
        "Image": "S1 - Midlysavage.png"
    },
    "Projectporo": {
        "Race": "Demi God",
        "Archetype": "",
        "Role": "?",
        "Title": "",
        "Size": "8.5FT",
        "Stats": {
            "Strength": "Cosmic",
            "Speed": "Supersonic",
            "Durability": "Nuclear",
            "IQ": "Genius",
            "Fight": "Meta-Martial"
        },
        "Weapons": {
            "Weapon": "",
            "Weapon Mastery": "Transcendent"
        },
        "Powers": {
            "Power": "Lightning + The Force",
            "Power Mastery": "Omnipotent"
        },
        "Extra": {
            "Weakness": "",
            "Chaos Force": "",
            "Chaos Factor": ""
        },
        "Enchantment": "",
        "Image": "S1 - Projectporo.png"
    },
    "Konstantinmuelle": {
        "Race": "Vacuum Robot",
        "Archetype": "",
        "Role": "?",
        "Title": "",
        "Size": "4.5FT",
        "Stats": {
            "Strength": "Peak Human",
            "Speed": "Old man",
            "Durability": "Mid",
            "IQ": "Genius",
            "Fight": "Mid"
        },
        "Weapons": {
            "Weapon": "Whip",
            "Weapon Mastery": "Transcendent"
        },
        "Powers": {
            "Power": "",
            "Power Mastery": "Omnipotent"
        },
        "Extra": {
            "Weakness": "",
            "Chaos Force": "",
            "Chaos Factor": ""
        },
        "Enchantment": "",
        "Image": "S1 - Konstantinmuelle.png"
    },
    "Plaguedexistence": {
        "Race": "Angel",
        "Archetype": "",
        "Role": "?",
        "Title": "",
        "Size": "8FT",
        "Stats": {
            "Strength": "Superhuman",
            "Speed": "Light Speed",
            "Durability": "Nuclear",
            "IQ": "Prodigious",
            "Fight": "Darwizzy"
        },
        "Weapons": {
            "Weapon": "",
            "Weapon Mastery": "Transcendent"
        },
        "Powers": {
            "Power": "Full counter + Energy projection",
            "Power Mastery": "Omnipotent"
        },
        "Extra": {
            "Weakness": "",
            "Chaos Force": "",
            "Chaos Factor": ""
        },
        "Enchantment": "",
        "Image": "S1 - Plaguedexistence.png"
    },
    "Buckhunter": {
        "Race": "Human",
        "Archetype": "",
        "Role": "?",
        "Title": "",
        "Size": "9.5FT",
        "Stats": {
            "Strength": "Boundless",
            "Speed": "Light Speed",
            "Durability": "Superhuman",
            "IQ": "Nigh-Omniscience",
            "Fight": "Darwizzy"
        },
        "Weapons": {
            "Weapon": "Lasso of truth",
            "Weapon Mastery": "Transcendent"
        },
        "Powers": {
            "Power": "Resurrection",
            "Power Mastery": "Omnipotent"
        },
        "Extra": {
            "Weakness": "",
            "Chaos Force": "",
            "Chaos Factor": ""
        },
        "Enchantment": "",
        "Image": "S1 - Buckhunter.png"
    },
    "Esaiesandoval": {
        "Race": "Werewolf",
        "Archetype": "",
        "Role": "?",
        "Title": "",
        "Size": "4FT",
        "Stats": {
            "Strength": "Herculean",
            "Speed": "Supersonic",
            "Durability": "Cosmic",
            "IQ": "Mid",
            "Fight": "Universal Gladiator"
        },
        "Weapons": {
            "Weapon": "Pillow",
            "Weapon Mastery": "Transcendent"
        },
        "Powers": {
            "Power": "Fire control",
            "Power Mastery": "Omnipotent"
        },
        "Extra": {
            "Weakness": "",
            "Chaos Force": "",
            "Chaos Factor": ""
        },
        "Enchantment": "",
        "Image": "S1 - Esaiesandoval.png"
    },
    "Astronautz": {
        "Race": "Goblin",
        "Archetype": "",
        "Role": "?",
        "Title": "",
        "Size": "4FT",
        "Stats": {
            "Strength": "Cosmic",
            "Speed": "Old man",
            "Durability": "Darwizzy",
            "IQ": "Mid",
            "Fight": "Mid"
        },
        "Weapons": {
            "Weapon": "Nunchaku",
            "Weapon Mastery": "Transcendent"
        },
        "Powers": {
            "Power": "Cloning",
            "Power Mastery": "Omnipotent"
        },
        "Extra": {
            "Weakness": "",
            "Chaos Force": "",
            "Chaos Factor": ""
        },
        "Enchantment": "",
        "Image": "S1 - Astronautz.png"
    },
    "Smithhunter": {
        "Race": "Cosmic Warrior",
        "Archetype": "",
        "Role": "?",
        "Title": "",
        "Size": "4FT",
        "Stats": {
            "Strength": "Infinite +1",
            "Speed": "Light Speed",
            "Durability": "Nuclear",
            "IQ": "Prodigious",
            "Fight": "Champion"
        },
        "Weapons": {
            "Weapon": "",
            "Weapon Mastery": "Transcendent"
        },
        "Powers": {
            "Power": "",
            "Power Mastery": "Omnipotent"
        },
        "Extra": {
            "Weakness": "",
            "Chaos Force": "",
            "Chaos Factor": ""
        },
        "Enchantment": "",
        "Image": "S1 - Smithhunter.png"
    },
    "Faith": {
        "Race": "Human NPC",
        "Archetype": "",
        "Role": "?",
        "Title": "",
        "Size": "4.5 Ft",
        "Stats": {
            "Strength": "Mid",
            "Speed": "Old man",
            "Durability": "Regenerative",
            "IQ": "Mid",
            "Fight": "Meta-Martial"
        },
        "Weapons": {
            "Weapon": "Brass Knuckles",
            "Weapon Mastery": "Transcendent"
        },
        "Powers": {
            "Power": "Reality Warping",
            "Power Mastery": "Omnipotent"
        },
        "Extra": {
            "Weakness": "",
            "Chaos Force": "",
            "Chaos Factor": ""
        },
        "Enchantment": "",
        "Image": ""
    }
}